MANIFEST.in
setup.py
tests/__init__.py
tests/test_entity.py
yaoguang/__init__.py
yaoguang/entity.py
yaoguang/exc.py
yaoguang/lead.py
yaoguang/static/yaoguang.thrift
yaoguang/static/yaoguang.thrift~
yaoguang_python_client.egg-info/PKG-INFO
yaoguang_python_client.egg-info/SOURCES.txt
yaoguang_python_client.egg-info/dependency_links.txt
yaoguang_python_client.egg-info/not-zip-safe
yaoguang_python_client.egg-info/requires.txt
yaoguang_python_client.egg-info/top_level.txt