Metadata-Version: 1.0
Name: yaoguang-python-client
Version: 0.0.9
Summary: baixing data service python client
Home-page: https://github.com/baixing/yaoguang
Author: onesuper
Author-email: onesuperclark@gmail.com
License: MIT
Platform: any
